assignments/hw2-tiny-processor/muxF.v


module muxF(
        input select,  // MF select
        input [31:0] input0,
        input [31:0] input1,
        output[31:0] out
    );

assign out = select ? input1 : input0;


endmodule

assignments/hw2-tiny-processor/barrelShifter.v


module barrelShifter(
    input [1:0] select,  // Operation select
    input [31:0] inB,    // 32-bit Input
    output [31:0] out    // 32-bit Output
    );


assign out = (select == 0) ? inB :       // s=0 -> Pass through
             (select == 1) ? inB >> 1 :  // s=1 -> Shift right
                             inB << 1;   // s=2 -> Shift left

endmodule

assignments/hw2-tiny-processor/alu.v

module ALU(
    input[2:0]  select,    // Function select
    input[31:0] a,         // 32-bit Input A
    input[31:0] b,         // 32-bit Input B
    input       carryIn,   // Carry in
    output[31:0] result,   // Output result
    output      carryOut,  // Carry out
    output      v          // Overflow
);

// Assign 32-bit result based on function select and carry in
assign {carryOut, result} = 
            (select == 0) ? 
                    (carryIn) ? a + 1 : a :             // s=0 -> Transfer a or increment a
            (select == 1) ? 
                    (carryIn) ? a + b + 1 : a + b :     // s=1 -> Add a and b with carry
            (select == 2) ? 
                    (carryIn) ? a + ~b + 1 : a + ~b :   // s=2 -> Add a and 1's complement of b
            (select == 3) ? 
                    (carryIn) ? a : a - 1 :             // s=3 -> transfer or Decrement a
            (select == 4) ? a & b :                     // s=4 -> a AND b
            (select == 5) ? a | b :                     // s=5 -> a OR b
            (select == 6) ? a ^ b :                     // s=6 -> a XOR b
            (select == 7) ? ~a :                        // s=7 -> NOT a
            4'b0; // Default

assign v = carryIn ^ carryOut;

endmodule

assignments/hw2-tiny-processor/function-unit.v
//=============================================================================
// HW2 Tiny Processor
// Mark Dannemiller
//=============================================================================
`include "alu.v"
`include "barrelShifter.v"
`include "muxF.v"

module functionUnit (
    input [4:0]     FS,    // Function select
    input [31:0]    inA,   // 32-bit Input A (for ALU)
    input [31:0]    inB,   // 32-bit Input B (for ALU and Barrel Shifter)

    output [31:0]   outF,  // 32-bit Output
    output          v,     // Overflow
    output          c,     // Carry out
    output          n,     // Negative flag
    output          zero   // Zero flag
);

// Selectors
wire MF_select;     // MuxF select
wire[3:0] gSelect;  // ALU function select
wire [1:0] hSelect; // Barrel shifter select

// Internal module outputs
wire [31:0] ALU_result;
wire [31:0] BS_result;
wire ALU_carryOut;
wire ALU_v;

// From table 7-10 select codes defined in terms of FS
assign MF_select = FS[4];
assign gSelect = FS[3:0];
assign hSelect = FS[3:2];

// Instantiate ALU
ALU alu(
    .select(gSelect[3:1]),
    .a(inA),
    .b(inB),
    .carryIn(gSelect[0]),
    .result(ALU_result),
    .carryOut(ALU_carryOut),
    .v(ALU_v)
);

// Instantiate Barrel Shifter
barrelShifter bs(
    .select(hSelect),
    .inB(inB),
    .out(BS_result)
);

// Instantiate MuxF to select between ALU and Barrel Shifter
muxF mf(
    .select(MF_select),
    .input0(ALU_result),
    .input1(BS_result),
    .out(outF)
);

// Set flags
assign v = ALU_v;
assign c = ALU_carryOut;
assign n = outF[31];
assign zero = (outF == 32'b0);

    
endmodule

assignments/hw2-tiny-processor/hw2_tb.v
//=============================================================================
// HW2 Tiny Processor
// Mark Dannemiller
//=============================================================================
`timescale 1ns/1ps
`include "function-unit.v"

module hw2_tb;

    // Test bench signals
    reg  [4:0]  FS;
    reg  [31:0] inA, inB;
    wire [31:0] outF;
    wire        v, c, n, zero;

    // Instantiate the function unit
    functionUnit dut (
        .FS (FS),
        .inA(inA),
        .inB(inB),
        .outF(outF),
        .v(v),
        .c(c),
        .n(n),
        .zero(zero)
    );

    // Test vectors
    reg [31:0] testAs [0:3];
    reg [31:0] testBs [0:3];
    integer i, j;

    initial begin
        // Initialize Inputs
        $dumpfile("hw2_tb.vcd");
        $dumpvars(0, hw2_tb);
        $display("Homework 2 Tiny Processor Testbench");

        // Interesting values for edge testing
        testAs[0] = 32'h00000000; 
        testAs[1] = 32'hFFFFFFFF; 
        testAs[2] = 32'h80000000; 
        testAs[3] = 32'hA5A5A5A5;
        testBs[0] = 32'h00000000;
        testBs[1] = 32'h00000001;
        testBs[2] = 32'h7FFFFFFF;
        testBs[3] = 32'h5A5A5A5A;

        $display("   FS inA      inB      outF     v c n z");
        for (FS = 0; FS < 25; FS = FS + 1) begin
            for (i = 0; i < 4; i = i + 1) begin
                for (j = 0; j < 4; j = j + 1) begin
                    inA = testAs[i]; inB = testBs[j];
                    #10;
                    $display("%5d %8h %8h %8h %1d %1d %1d %1d", FS, inA, inB, outF, v, c, n, zero);
                end
            end
        end
    end

endmodule

assignments/hw2-tiny-processor/hw2_tb.vcd
$date
	Thu Jan 30 14:20:32 2025
$end
$version
	Icarus Verilog
$end
$timescale
	1ps
$end
$scope module hw2_tb $end
$var wire 1 ! zero $end
$var wire 1 " v $end
$var wire 32 # outF [31:0] $end
$var wire 1 $ n $end
$var wire 1 % c $end
$var reg 5 & FS [4:0] $end
$var reg 32 ' inA [31:0] $end
$var reg 32 ( inB [31:0] $end
$var integer 32 ) i [31:0] $end
$var integer 32 * j [31:0] $end
$scope module dut $end
$var wire 5 + FS [4:0] $end
$var wire 1 % c $end
$var wire 32 , inA [31:0] $end
$var wire 32 - inB [31:0] $end
$var wire 1 " v $end
$var wire 1 ! zero $end
$var wire 32 . outF [31:0] $end
$var wire 1 $ n $end
$var wire 2 / hSelect [1:0] $end
$var wire 4 0 gSelect [3:0] $end
$var wire 1 1 MF_select $end
$var wire 32 2 BS_result [31:0] $end
$var wire 1 3 ALU_v $end
$var wire 32 4 ALU_result [31:0] $end
$var wire 1 5 ALU_carryOut $end
$scope module alu $end
$var wire 32 6 a [31:0] $end
$var wire 32 7 b [31:0] $end
$var wire 1 8 carryIn $end
$var wire 3 9 select [2:0] $end
$var wire 1 3 v $end
$var wire 32 : result [31:0] $end
$var wire 1 5 carryOut $end
$upscope $end
$scope module bs $end
$var wire 32 ; inB [31:0] $end
$var wire 2 < select [1:0] $end
$var wire 32 = out [31:0] $end
$upscope $end
$scope module mf $end
$var wire 32 > input0 [31:0] $end
$var wire 32 ? input1 [31:0] $end
$var wire 1 1 select $end
$var wire 32 @ out [31:0] $end
$upscope $end
$upscope $end
$upscope $end
$enddefinitions $end
$comment Show the parameter values. $end
$dumpall
$end
#0
$dumpvars
b0 @
b0 ?
b0 >
b0 =
b0 <
b0 ;
b0 :
b0 9
08
b0 7
b0 6
05
b0 4
03
b0 2
01
b0 0
b0 /
b0 .
b0 -
b0 ,
b0 +
b0 *
b0 )
b0 (
b0 '
b0 &
0%
0$
b0 #
0"
1!
$end
#10000
b1 2
b1 =
b1 ?
b1 (
b1 -
b1 7
b1 ;
b1 *
#20000
b1111111111111111111111111111111 2
b1111111111111111111111111111111 =
b1111111111111111111111111111111 ?
b1111111111111111111111111111111 (
b1111111111111111111111111111111 -
b1111111111111111111111111111111 7
b1111111111111111111111111111111 ;
b10 *
#30000
b1011010010110100101101001011010 2
b1011010010110100101101001011010 =
b1011010010110100101101001011010 ?
b1011010010110100101101001011010 (
b1011010010110100101101001011010 -
b1011010010110100101101001011010 7
b1011010010110100101101001011010 ;
b11 *
#40000
1$
0!
b11111111111111111111111111111111 #
b11111111111111111111111111111111 .
b11111111111111111111111111111111 @
b11111111111111111111111111111111 4
b11111111111111111111111111111111 :
b11111111111111111111111111111111 >
b0 2
b0 =
b0 ?
b0 (
b0 -
b0 7
b0 ;
b11111111111111111111111111111111 '
b11111111111111111111111111111111 ,
b11111111111111111111111111111111 6
b1 )
b0 *
#50000
b1 2
b1 =
b1 ?
b1 (
b1 -
b1 7
b1 ;
b1 *
#60000
b1111111111111111111111111111111 2
b1111111111111111111111111111111 =
b1111111111111111111111111111111 ?
b1111111111111111111111111111111 (
b1111111111111111111111111111111 -
b1111111111111111111111111111111 7
b1111111111111111111111111111111 ;
b10 *
#70000
b1011010010110100101101001011010 2
b1011010010110100101101001011010 =
b1011010010110100101101001011010 ?
b1011010010110100101101001011010 (
b1011010010110100101101001011010 -
b1011010010110100101101001011010 7
b1011010010110100101101001011010 ;
b11 *
#80000
b10000000000000000000000000000000 #
b10000000000000000000000000000000 .
b10000000000000000000000000000000 @
b10000000000000000000000000000000 4
b10000000000000000000000000000000 :
b10000000000000000000000000000000 >
b0 2
b0 =
b0 ?
b0 (
b0 -
b0 7
b0 ;
b10000000000000000000000000000000 '
b10000000000000000000000000000000 ,
b10000000000000000000000000000000 6
b10 )
b0 *
#90000
b1 2
b1 =
b1 ?
b1 (
b1 -
b1 7
b1 ;
b1 *
#100000
b1111111111111111111111111111111 2
b1111111111111111111111111111111 =
b1111111111111111111111111111111 ?
b1111111111111111111111111111111 (
b1111111111111111111111111111111 -
b1111111111111111111111111111111 7
b1111111111111111111111111111111 ;
b10 *
#110000
b1011010010110100101101001011010 2
b1011010010110100101101001011010 =
b1011010010110100101101001011010 ?
b1011010010110100101101001011010 (
b1011010010110100101101001011010 -
b1011010010110100101101001011010 7
b1011010010110100101101001011010 ;
b11 *
#120000
b10100101101001011010010110100101 #
b10100101101001011010010110100101 .
b10100101101001011010010110100101 @
b10100101101001011010010110100101 4
b10100101101001011010010110100101 :
b10100101101001011010010110100101 >
b0 2
b0 =
b0 ?
b0 (
b0 -
b0 7
b0 ;
b10100101101001011010010110100101 '
b10100101101001011010010110100101 ,
b10100101101001011010010110100101 6
b11 )
b0 *
#130000
b1 2
b1 =
b1 ?
b1 (
b1 -
b1 7
b1 ;
b1 *
#140000
b1111111111111111111111111111111 2
b1111111111111111111111111111111 =
b1111111111111111111111111111111 ?
b1111111111111111111111111111111 (
b1111111111111111111111111111111 -
b1111111111111111111111111111111 7
b1111111111111111111111111111111 ;
b10 *
#150000
b1011010010110100101101001011010 2
b1011010010110100101101001011010 =
b1011010010110100101101001011010 ?
b1011010010110100101101001011010 (
b1011010010110100101101001011010 -
b1011010010110100101101001011010 7
b1011010010110100101101001011010 ;
b11 *
#160000
0$
0!
b1 #
b1 .
b1 @
b1 4
b1 :
b1 >
1"
13
18
b0 2
b0 =
b0 ?
b1 0
b0 (
b0 -
b0 7
b0 ;
b0 '
b0 ,
b0 6
b1 &
b1 +
b0 )
b0 *
#170000
b1 2
b1 =
b1 ?
b1 (
b1 -
b1 7
b1 ;
b1 *
#180000
b1111111111111111111111111111111 2
b1111111111111111111111111111111 =
b1111111111111111111111111111111 ?
b1111111111111111111111111111111 (
b1111111111111111111111111111111 -
b1111111111111111111111111111111 7
b1111111111111111111111111111111 ;
b10 *
#190000
b1011010010110100101101001011010 2
b1011010010110100101101001011010 =
b1011010010110100101101001011010 ?
b1011010010110100101101001011010 (
b1011010010110100101101001011010 -
b1011010010110100101101001011010 7
b1011010010110100101101001011010 ;
b11 *
#200000
1!
b0 #
b0 .
b0 @
0"
03
b0 4
b0 :
b0 >
1%
15
b0 2
b0 =
b0 ?
b0 (
b0 -
b0 7
b0 ;
b11111111111111111111111111111111 '
b11111111111111111111111111111111 ,
b11111111111111111111111111111111 6
b1 )
b0 *
#210000
b1 2
b1 =
b1 ?
b1 (
b1 -
b1 7
b1 ;
b1 *
#220000
b1111111111111111111111111111111 2
b1111111111111111111111111111111 =
b1111111111111111111111111111111 ?
b1111111111111111111111111111111 (
b1111111111111111111111111111111 -
b1111111111111111111111111111111 7
b1111111111111111111111111111111 ;
b10 *
#230000
b1011010010110100101101001011010 2
b1011010010110100101101001011010 =
b1011010010110100101101001011010 ?
b1011010010110100101101001011010 (
b1011010010110100101101001011010 -
b1011010010110100101101001011010 7
b1011010010110100101101001011010 ;
b11 *
#240000
1$
0!
b10000000000000000000000000000001 #
b10000000000000000000000000000001 .
b10000000000000000000000000000001 @
1"
13
b10000000000000000000000000000001 4
b10000000000000000000000000000001 :
b10000000000000000000000000000001 >
0%
05
b0 2
b0 =
b0 ?
b0 (
b0 -
b0 7
b0 ;
b10000000000000000000000000000000 '
b10000000000000000000000000000000 ,
b10000000000000000000000000000000 6
b10 )
b0 *
#250000
b1 2
b1 =
b1 ?
b1 (
b1 -
b1 7
b1 ;
b1 *
#260000
b1111111111111111111111111111111 2
b1111111111111111111111111111111 =
b1111111111111111111111111111111 ?
b1111111111111111111111111111111 (
b1111111111111111111111111111111 -
b1111111111111111111111111111111 7
b1111111111111111111111111111111 ;
b10 *
#270000
b1011010010110100101101001011010 2
b1011010010110100101101001011010 =
b1011010010110100101101001011010 ?
b1011010010110100101101001011010 (
b1011010010110100101101001011010 -
b1011010010110100101101001011010 7
b1011010010110100101101001011010 ;
b11 *
#280000
b10100101101001011010010110100110 #
b10100101101001011010010110100110 .
b10100101101001011010010110100110 @
b10100101101001011010010110100110 4
b10100101101001011010010110100110 :
b10100101101001011010010110100110 >
b0 2
b0 =
b0 ?
b0 (
b0 -
b0 7
b0 ;
b10100101101001011010010110100101 '
b10100101101001011010010110100101 ,
b10100101101001011010010110100101 6
b11 )
b0 *
#290000
b1 2
b1 =
b1 ?
b1 (
b1 -
b1 7
b1 ;
b1 *
#300000
b1111111111111111111111111111111 2
b1111111111111111111111111111111 =
b1111111111111111111111111111111 ?
b1111111111111111111111111111111 (
b1111111111111111111111111111111 -
b1111111111111111111111111111111 7
b1111111111111111111111111111111 ;
b10 *
#310000
b1011010010110100101101001011010 2
b1011010010110100101101001011010 =
b1011010010110100101101001011010 ?
b1011010010110100101101001011010 (
b1011010010110100101101001011010 -
b1011010010110100101101001011010 7
b1011010010110100101101001011010 ;
b11 *
#320000
0$
1!
b0 #
b0 .
b0 @
b0 4
b0 :
b0 >
0"
03
b1 9
08
b0 2
b0 =
b0 ?
b10 0
b0 (
b0 -
b0 7
b0 ;
b0 '
b0 ,
b0 6
b10 &
b10 +
b0 )
b0 *
#330000
0!
b1 #
b1 .
b1 @
b1 4
b1 :
b1 >
b1 2
b1 =
b1 ?
b1 (
b1 -
b1 7
b1 ;
b1 *
#340000
b1111111111111111111111111111111 #
b1111111111111111111111111111111 .
b1111111111111111111111111111111 @
b1111111111111111111111111111111 4
b1111111111111111111111111111111 :
b1111111111111111111111111111111 >
b1111111111111111111111111111111 2
b1111111111111111111111111111111 =
b1111111111111111111111111111111 ?
b1111111111111111111111111111111 (
b1111111111111111111111111111111 -
b1111111111111111111111111111111 7
b1111111111111111111111111111111 ;
b10 *
#350000
b1011010010110100101101001011010 #
b1011010010110100101101001011010 .
b1011010010110100101101001011010 @
b1011010010110100101101001011010 4
b1011010010110100101101001011010 :
b1011010010110100101101001011010 >
b1011010010110100101101001011010 2
b1011010010110100101101001011010 =
b1011010010110100101101001011010 ?
b1011010010110100101101001011010 (
b1011010010110100101101001011010 -
b1011010010110100101101001011010 7
b1011010010110100101101001011010 ;
b11 *
#360000
1$
b11111111111111111111111111111111 #
b11111111111111111111111111111111 .
b11111111111111111111111111111111 @
b11111111111111111111111111111111 4
b11111111111111111111111111111111 :
b11111111111111111111111111111111 >
b0 2
b0 =
b0 ?
b0 (
b0 -
b0 7
b0 ;
b11111111111111111111111111111111 '
b11111111111111111111111111111111 ,
b11111111111111111111111111111111 6
b1 )
b0 *
#370000
0$
1!
b0 #
b0 .
b0 @
1"
13
b0 4
b0 :
b0 >
1%
15
b1 2
b1 =
b1 ?
b1 (
b1 -
b1 7
b1 ;
b1 *
#380000
0!
b1111111111111111111111111111110 #
b1111111111111111111111111111110 .
b1111111111111111111111111111110 @
b1111111111111111111111111111110 4
b1111111111111111111111111111110 :
b1111111111111111111111111111110 >
b1111111111111111111111111111111 2
b1111111111111111111111111111111 =
b1111111111111111111111111111111 ?
b1111111111111111111111111111111 (
b1111111111111111111111111111111 -
b1111111111111111111111111111111 7
b1111111111111111111111111111111 ;
b10 *
#390000
b1011010010110100101101001011001 #
b1011010010110100101101001011001 .
b1011010010110100101101001011001 @
b1011010010110100101101001011001 4
b1011010010110100101101001011001 :
b1011010010110100101101001011001 >
b1011010010110100101101001011010 2
b1011010010110100101101001011010 =
b1011010010110100101101001011010 ?
b1011010010110100101101001011010 (
b1011010010110100101101001011010 -
b1011010010110100101101001011010 7
b1011010010110100101101001011010 ;
b11 *
#400000
1$
b10000000000000000000000000000000 #
b10000000000000000000000000000000 .
b10000000000000000000000000000000 @
0"
03
b10000000000000000000000000000000 4
b10000000000000000000000000000000 :
b10000000000000000000000000000000 >
0%
05
b0 2
b0 =
b0 ?
b0 (
b0 -
b0 7
b0 ;
b10000000000000000000000000000000 '
b10000000000000000000000000000000 ,
b10000000000000000000000000000000 6
b10 )
b0 *
#410000
b10000000000000000000000000000001 #
b10000000000000000000000000000001 .
b10000000000000000000000000000001 @
b10000000000000000000000000000001 4
b10000000000000000000000000000001 :
b10000000000000000000000000000001 >
b1 2
b1 =
b1 ?
b1 (
b1 -
b1 7
b1 ;
b1 *
#420000
b11111111111111111111111111111111 #
b11111111111111111111111111111111 .
b11111111111111111111111111111111 @
b11111111111111111111111111111111 4
b11111111111111111111111111111111 :
b11111111111111111111111111111111 >
b1111111111111111111111111111111 2
b1111111111111111111111111111111 =
b1111111111111111111111111111111 ?
b1111111111111111111111111111111 (
b1111111111111111111111111111111 -
b1111111111111111111111111111111 7
b1111111111111111111111111111111 ;
b10 *
#430000
b11011010010110100101101001011010 #
b11011010010110100101101001011010 .
b11011010010110100101101001011010 @
b11011010010110100101101001011010 4
b11011010010110100101101001011010 :
b11011010010110100101101001011010 >
b1011010010110100101101001011010 2
b1011010010110100101101001011010 =
b1011010010110100101101001011010 ?
b1011010010110100101101001011010 (
b1011010010110100101101001011010 -
b1011010010110100101101001011010 7
b1011010010110100101101001011010 ;
b11 *
#440000
b10100101101001011010010110100101 #
b10100101101001011010010110100101 .
b10100101101001011010010110100101 @
b10100101101001011010010110100101 4
b10100101101001011010010110100101 :
b10100101101001011010010110100101 >
b0 2
b0 =
b0 ?
b0 (
b0 -
b0 7
b0 ;
b10100101101001011010010110100101 '
b10100101101001011010010110100101 ,
b10100101101001011010010110100101 6
b11 )
b0 *
#450000
b10100101101001011010010110100110 #
b10100101101001011010010110100110 .
b10100101101001011010010110100110 @
b10100101101001011010010110100110 4
b10100101101001011010010110100110 :
b10100101101001011010010110100110 >
b1 2
b1 =
b1 ?
b1 (
b1 -
b1 7
b1 ;
b1 *
#460000
0$
b100101101001011010010110100100 #
b100101101001011010010110100100 .
b100101101001011010010110100100 @
1"
13
b100101101001011010010110100100 4
b100101101001011010010110100100 :
b100101101001011010010110100100 >
1%
15
b1111111111111111111111111111111 2
b1111111111111111111111111111111 =
b1111111111111111111111111111111 ?
b1111111111111111111111111111111 (
b1111111111111111111111111111111 -
b1111111111111111111111111111111 7
b1111111111111111111111111111111 ;
b10 *
#470000
1$
b11111111111111111111111111111111 #
b11111111111111111111111111111111 .
b11111111111111111111111111111111 @
0"
03
b11111111111111111111111111111111 4
b11111111111111111111111111111111 :
b11111111111111111111111111111111 >
0%
05
b1011010010110100101101001011010 2
b1011010010110100101101001011010 =
b1011010010110100101101001011010 ?
b1011010010110100101101001011010 (
b1011010010110100101101001011010 -
b1011010010110100101101001011010 7
b1011010010110100101101001011010 ;
b11 *
#480000
0$
0!
b1 #
b1 .
b1 @
b1 4
b1 :
b1 >
1"
13
18
b0 2
b0 =
b0 ?
b11 0
b0 (
b0 -
b0 7
b0 ;
b0 '
b0 ,
b0 6
b11 &
b11 +
b0 )
b0 *
#490000
b10 #
b10 .
b10 @
b10 4
b10 :
b10 >
b1 2
b1 =
b1 ?
b1 (
b1 -
b1 7
b1 ;
b1 *
#500000
1$
b10000000000000000000000000000000 #
b10000000000000000000000000000000 .
b10000000000000000000000000000000 @
b10000000000000000000000000000000 4
b10000000000000000000000000000000 :
b10000000000000000000000000000000 >
b1111111111111111111111111111111 2
b1111111111111111111111111111111 =
b1111111111111111111111111111111 ?
b1111111111111111111111111111111 (
b1111111111111111111111111111111 -
b1111111111111111111111111111111 7
b1111111111111111111111111111111 ;
b10 *
#510000
0$
b1011010010110100101101001011011 #
b1011010010110100101101001011011 .
b1011010010110100101101001011011 @
b1011010010110100101101001011011 4
b1011010010110100101101001011011 :
b1011010010110100101101001011011 >
b1011010010110100101101001011010 2
b1011010010110100101101001011010 =
b1011010010110100101101001011010 ?
b1011010010110100101101001011010 (
b1011010010110100101101001011010 -
b1011010010110100101101001011010 7
b1011010010110100101101001011010 ;
b11 *
#520000
1!
b0 #
b0 .
b0 @
0"
03
b0 4
b0 :
b0 >
1%
15
b0 2
b0 =
b0 ?
b0 (
b0 -
b0 7
b0 ;
b11111111111111111111111111111111 '
b11111111111111111111111111111111 ,
b11111111111111111111111111111111 6
b1 )
b0 *
#530000
0!
b1 #
b1 .
b1 @
b1 4
b1 :
b1 >
b1 2
b1 =
b1 ?
b1 (
b1 -
b1 7
b1 ;
b1 *
#540000
b1111111111111111111111111111111 #
b1111111111111111111111111111111 .
b1111111111111111111111111111111 @
b1111111111111111111111111111111 4
b1111111111111111111111111111111 :
b1111111111111111111111111111111 >
b1111111111111111111111111111111 2
b1111111111111111111111111111111 =
b1111111111111111111111111111111 ?
b1111111111111111111111111111111 (
b1111111111111111111111111111111 -
b1111111111111111111111111111111 7
b1111111111111111111111111111111 ;
b10 *
#550000
b1011010010110100101101001011010 #
b1011010010110100101101001011010 .
b1011010010110100101101001011010 @
b1011010010110100101101001011010 4
b1011010010110100101101001011010 :
b1011010010110100101101001011010 >
b1011010010110100101101001011010 2
b1011010010110100101101001011010 =
b1011010010110100101101001011010 ?
b1011010010110100101101001011010 (
b1011010010110100101101001011010 -
b1011010010110100101101001011010 7
b1011010010110100101101001011010 ;
b11 *
#560000
1$
b10000000000000000000000000000001 #
b10000000000000000000000000000001 .
b10000000000000000000000000000001 @
1"
13
b10000000000000000000000000000001 4
b10000000000000000000000000000001 :
b10000000000000000000000000000001 >
0%
05
b0 2
b0 =
b0 ?
b0 (
b0 -
b0 7
b0 ;
b10000000000000000000000000000000 '
b10000000000000000000000000000000 ,
b10000000000000000000000000000000 6
b10 )
b0 *
#570000
b10000000000000000000000000000010 #
b10000000000000000000000000000010 .
b10000000000000000000000000000010 @
b10000000000000000000000000000010 4
b10000000000000000000000000000010 :
b10000000000000000000000000000010 >
b1 2
b1 =
b1 ?
b1 (
b1 -
b1 7
b1 ;
b1 *
#580000
0$
1!
b0 #
b0 .
b0 @
0"
03
b0 4
b0 :
b0 >
1%
15
b1111111111111111111111111111111 2
b1111111111111111111111111111111 =
b1111111111111111111111111111111 ?
b1111111111111111111111111111111 (
b1111111111111111111111111111111 -
b1111111111111111111111111111111 7
b1111111111111111111111111111111 ;
b10 *
#590000
1$
0!
b11011010010110100101101001011011 #
b11011010010110100101101001011011 .
b11011010010110100101101001011011 @
1"
13
b11011010010110100101101001011011 4
b11011010010110100101101001011011 :
b11011010010110100101101001011011 >
0%
05
b1011010010110100101101001011010 2
b1011010010110100101101001011010 =
b1011010010110100101101001011010 ?
b1011010010110100101101001011010 (
b1011010010110100101101001011010 -
b1011010010110100101101001011010 7
b1011010010110100101101001011010 ;
b11 *
#600000
b10100101101001011010010110100110 #
b10100101101001011010010110100110 .
b10100101101001011010010110100110 @
b10100101101001011010010110100110 4
b10100101101001011010010110100110 :
b10100101101001011010010110100110 >
b0 2
b0 =
b0 ?
b0 (
b0 -
b0 7
b0 ;
b10100101101001011010010110100101 '
b10100101101001011010010110100101 ,
b10100101101001011010010110100101 6
b11 )
b0 *
#610000
b10100101101001011010010110100111 #
b10100101101001011010010110100111 .
b10100101101001011010010110100111 @
b10100101101001011010010110100111 4
b10100101101001011010010110100111 :
b10100101101001011010010110100111 >
b1 2
b1 =
b1 ?
b1 (
b1 -
b1 7
b1 ;
b1 *
#620000
0$
b100101101001011010010110100101 #
b100101101001011010010110100101 .
b100101101001011010010110100101 @
0"
03
b100101101001011010010110100101 4
b100101101001011010010110100101 :
b100101101001011010010110100101 >
1%
15
b1111111111111111111111111111111 2
b1111111111111111111111111111111 =
b1111111111111111111111111111111 ?
b1111111111111111111111111111111 (
b1111111111111111111111111111111 -
b1111111111111111111111111111111 7
b1111111111111111111111111111111 ;
b10 *
#630000
1!
b0 #
b0 .
b0 @
b0 4
b0 :
b0 >
b1011010010110100101101001011010 2
b1011010010110100101101001011010 =
b1011010010110100101101001011010 ?
b1011010010110100101101001011010 (
b1011010010110100101101001011010 -
b1011010010110100101101001011010 7
b1011010010110100101101001011010 ;
b11 *
#640000
1$
0!
b11111111111111111111111111111111 #
b11111111111111111111111111111111 .
b11111111111111111111111111111111 @
b11111111111111111111111111111111 4
b11111111111111111111111111111111 :
b11111111111111111111111111111111 >
1%
15
1"
13
b10 9
08
b0 2
b0 =
b0 ?
b100 0
b1 /
b1 <
b0 (
b0 -
b0 7
b0 ;
b0 '
b0 ,
b0 6
b100 &
b100 +
b0 )
b0 *
#650000
b11111111111111111111111111111110 #
b11111111111111111111111111111110 .
b11111111111111111111111111111110 @
b11111111111111111111111111111110 4
b11111111111111111111111111111110 :
b11111111111111111111111111111110 >
b1 (
b1 -
b1 7
b1 ;
b1 *
#660000
b10000000000000000000000000000000 #
b10000000000000000000000000000000 .
b10000000000000000000000000000000 @
b10000000000000000000000000000000 4
b10000000000000000000000000000000 :
b10000000000000000000000000000000 >
b111111111111111111111111111111 2
b111111111111111111111111111111 =
b111111111111111111111111111111 ?
b1111111111111111111111111111111 (
b1111111111111111111111111111111 -
b1111111111111111111111111111111 7
b1111111111111111111111111111111 ;
b10 *
#670000
b10100101101001011010010110100101 #
b10100101101001011010010110100101 .
b10100101101001011010010110100101 @
b10100101101001011010010110100101 4
b10100101101001011010010110100101 :
b10100101101001011010010110100101 >
b101101001011010010110100101101 2
b101101001011010010110100101101 =
b101101001011010010110100101101 ?
b1011010010110100101101001011010 (
b1011010010110100101101001011010 -
b1011010010110100101101001011010 7
b1011010010110100101101001011010 ;
b11 *
#680000
b11111111111111111111111111111110 #
b11111111111111111111111111111110 .
b11111111111111111111111111111110 @
0"
03
b11111111111111111111111111111110 4
b11111111111111111111111111111110 :
b11111111111111111111111111111110 >
0%
05
b0 2
b0 =
b0 ?
b0 (
b0 -
b0 7
b0 ;
b11111111111111111111111111111111 '
b11111111111111111111111111111111 ,
b11111111111111111111111111111111 6
b1 )
b0 *
#690000
b11111111111111111111111111111101 #
b11111111111111111111111111111101 .
b11111111111111111111111111111101 @
b11111111111111111111111111111101 4
b11111111111111111111111111111101 :
b11111111111111111111111111111101 >
b1 (
b1 -
b1 7
b1 ;
b1 *
#700000
0$
b1111111111111111111111111111111 #
b1111111111111111111111111111111 .
b1111111111111111111111111111111 @
b1111111111111111111111111111111 4
b1111111111111111111111111111111 :
b1111111111111111111111111111111 >
b111111111111111111111111111111 2
b111111111111111111111111111111 =
b111111111111111111111111111111 ?
b1111111111111111111111111111111 (
b1111111111111111111111111111111 -
b1111111111111111111111111111111 7
b1111111111111111111111111111111 ;
b10 *
#710000
1$
b10100101101001011010010110100100 #
b10100101101001011010010110100100 .
b10100101101001011010010110100100 @
b10100101101001011010010110100100 4
b10100101101001011010010110100100 :
b10100101101001011010010110100100 >
b101101001011010010110100101101 2
b101101001011010010110100101101 =
b101101001011010010110100101101 ?
b1011010010110100101101001011010 (
b1011010010110100101101001011010 -
b1011010010110100101101001011010 7
b1011010010110100101101001011010 ;
b11 *
#720000
0$
b1111111111111111111111111111111 #
b1111111111111111111111111111111 .
b1111111111111111111111111111111 @
b1111111111111111111111111111111 4
b1111111111111111111111111111111 :
b1111111111111111111111111111111 >
b0 2
b0 =
b0 ?
b0 (
b0 -
b0 7
b0 ;
b10000000000000000000000000000000 '
b10000000000000000000000000000000 ,
b10000000000000000000000000000000 6
b10 )
b0 *
#730000
b1111111111111111111111111111110 #
b1111111111111111111111111111110 .
b1111111111111111111111111111110 @
b1111111111111111111111111111110 4
b1111111111111111111111111111110 :
b1111111111111111111111111111110 >
b1 (
b1 -
b1 7
b1 ;
b1 *
#740000
1!
b0 #
b0 .
b0 @
b0 4
b0 :
b0 >
b111111111111111111111111111111 2
b111111111111111111111111111111 =
b111111111111111111111111111111 ?
b1111111111111111111111111111111 (
b1111111111111111111111111111111 -
b1111111111111111111111111111111 7
b1111111111111111111111111111111 ;
b10 *
#750000
0!
b100101101001011010010110100101 #
b100101101001011010010110100101 .
b100101101001011010010110100101 @
b100101101001011010010110100101 4
b100101101001011010010110100101 :
b100101101001011010010110100101 >
b101101001011010010110100101101 2
b101101001011010010110100101101 =
b101101001011010010110100101101 ?
b1011010010110100101101001011010 (
b1011010010110100101101001011010 -
b1011010010110100101101001011010 7
b1011010010110100101101001011010 ;
b11 *
#760000
1$
b10100101101001011010010110100100 #
b10100101101001011010010110100100 .
b10100101101001011010010110100100 @
b10100101101001011010010110100100 4
b10100101101001011010010110100100 :
b10100101101001011010010110100100 >
b0 2
b0 =
b0 ?
b0 (
b0 -
b0 7
b0 ;
b10100101101001011010010110100101 '
b10100101101001011010010110100101 ,
b10100101101001011010010110100101 6
b11 )
b0 *
#770000
b10100101101001011010010110100011 #
b10100101101001011010010110100011 .
b10100101101001011010010110100011 @
b10100101101001011010010110100011 4
b10100101101001011010010110100011 :
b10100101101001011010010110100011 >
b1 (
b1 -
b1 7
b1 ;
b1 *
#780000
0$
b100101101001011010010110100101 #
b100101101001011010010110100101 .
b100101101001011010010110100101 @
b100101101001011010010110100101 4
b100101101001011010010110100101 :
b100101101001011010010110100101 >
b111111111111111111111111111111 2
b111111111111111111111111111111 =
b111111111111111111111111111111 ?
b1111111111111111111111111111111 (
b1111111111111111111111111111111 -
b1111111111111111111111111111111 7
b1111111111111111111111111111111 ;
b10 *
