assignments/hw5-risc-cpu/instructionMemory.v
module instructionMemory(
    input wire [31:0] addr,        // Address input
    output wire [31:0] instruction // Instruction output
);
    /*
     * Instruction Memory - Pipeline Stage: Instruction Fetch (IF)
     * 
     * This module represents the instruction memory in the first stage of the pipeline.
     * It stores the program instructions and outputs them based on the PC address.
     * Each instruction is 32 bits wide, and the memory can store 1024 instructions.
     * The module is read-only and combinational, providing instructions immediately
     * without any clock delay.
     */

    integer i;  // Index for memory array

    // Memory array (1024 instructions, each 32 bits)
    reg [31:0] memory [0:1023];

    // Combinational read operation
    assign instruction = memory[addr[9:0]];  // Use lower 10 bits for addressing

    // Initialize memory
    initial begin
        // Initialize all memory locations to NOP
        for (i = 0; i < 1024; i = i + 1)
            memory[i] = 32'h00000000;
    end

endmodule

assignments/hw5-risc-cpu/muxC.v
module muxC(
    input wire [31:0] PC_1,      // PC+1 value
    input wire [31:0] BrA,       // Branch address
    input wire [31:0] RAA,       // Register A address
    input wire [31:0] JMP,       // Jump address
    input wire [1:0] BS,         // Branch Select
    input wire PS,               // Program Select (single bit)
    input wire Z,                // Zero flag
    output wire [31:0] out       // Selected output
);
    /*
     * Multiplexer C - Pipeline Stage: Instruction Fetch (IF)
     * 
     * This multiplexer controls program flow by selecting the next PC value.
     * The design shown in the diagram uses a combination of AND, OR gates
     * with BS1 (high bit of BS) controlling the upper MUX path.
     * 
     * Control logic:
     * - BS=00: Select PC+1 (sequential execution)
     * - BS=01 and PS=0: BZ - Branch if Zero (select BrA if Z=1)
     * - BS=01 and PS=1: BNZ - Branch if Not Zero (select BrA if Z=0)
     * - BS=10: JMR - Jump to Register (select RAA)
     * - BS=11: JMP - Jump to immediate (select JMP)
     */

    // BS[1] (high bit) controls whether PC+1/conditional branch or JMR/JMP is selected
    wire BS1 = BS[1];
    wire BS0 = BS[0];
    
    // Control for conditional branch
    wire branch_condition = PS ? ~Z : Z;  // BNZ: Branch if Z=0, BZ: Branch if Z=1
    
    // BS0 determines whether to use BrA (conditional branch) or PC+1
    wire [31:0] top_path = (BS0 & branch_condition) ? BrA : PC_1;
    
    // BS0 determines whether to use JMP (unconditional jump) or RAA (jump register) 
    wire [31:0] bottom_path = BS0 ? JMP : RAA;
    
    // BS1 selects between top path (sequential/conditional) and bottom path (jumps)
    assign out = BS1 ? bottom_path : top_path;

endmodule

assignments/hw5-risc-cpu/IF_stage.v
module IF_stage(
    input wire clk,                  // System clock signal that drives pipeline timing
    input wire rst,                  // Active-high reset signal to initialize components
    input wire [31:0] PC,            // Current Program Counter value from top module (points to instruction to fetch)
    input wire [31:0] BrA,           // Branch target address - calculated in EX stage for conditional branches
    input wire [31:0] RAA,           // Register jump address - used for JMR (Jump Register) instruction, sourced from register
    input wire [31:0] JMP,           // Jump target address - used for JMP (Jump Immediate) instruction
    input wire [1:0] BS,             // Branch Select control - determines type of branch/jump: 00=no branch, 01=conditional, 10=register, 11=direct
    input wire PS,                   // Program Select control - selects branch condition polarity: 0=branch if Z, 1=branch if !Z
    input wire Z,                    // Zero flag from ALU in EX stage - used for conditional branch decisions
    output wire [31:0] PC_next,      // Next PC value output - will become the new PC on next clock cycle
    output wire [31:0] PC_1,         // PC + 1 value - used for sequential execution and as return address for jump-and-link
    output wire [31:0] instruction   // Current instruction fetched from instruction memory at address PC
);
    /*
     * Instruction Fetch (IF) Stage - First stage of 4-stage RISC CPU pipeline
     *
     * Purpose and Operation:
     * ---------------------
     * The IF stage is responsible for fetching the current instruction pointed to by PC
     * and determining the next PC value based on branch/jump conditions.
     *
     * This stage coordinates three key operations:
     * 1. Reading the instruction at the current PC from instruction memory
     * 2. Incrementing PC to PC+1 for potential sequential execution
     * 3. Selecting the next PC value based on control signals and condition flags
     *
     * The PC update actually happens in the top module, where PC is stored in a
     * pipeline register and updated on the negative clock edge.
     *
     * Branch/Jump Selection Logic:
     * --------------------------
     * The MuxC component selects the next PC value from four possible sources:
     * - PC+1: Sequential execution (next instruction)
     * - BrA: Branch target address (for conditional branches)
     * - RAA: Register address (for jumps to address in register)
     * - JMP: Jump target address (for direct jumps)
     *
     * The selection is controlled by BS (Branch Select) and the branch 
     * condition is determined by PS (Program Select) and Z (Zero flag).
     */

    // Calculate PC+1 for sequential execution and branch calculations
    // This is used both for sequential execution and as a return address for jump-and-link
    assign PC_1 = PC + 32'h1;
    
    // Instruction Memory - Retrieves the instruction at the current PC address
    // This is an asynchronous read operation - the instruction is available immediately
    instructionMemory inst_mem(
        .addr(PC),                // Current PC value as memory address
        .instruction(instruction)  // Fetched instruction output
    );

    // MuxC - Next PC Selection Multiplexer
    // Determines the next PC value based on branch/jump control signals
    muxC mux_c(
        .PC_1(PC_1),          // PC+1 for sequential execution (no branch/jump)
        .BrA(BrA),            // Branch target address (for conditional branches - BZ/BNZ)
        .RAA(RAA),            // Register jump target (for JMR - Jump to Register)
        .JMP(JMP),            // Immediate jump target (for JMP - Jump Immediate)
        .BS(BS),              // Branch Select control - determines branch/jump type
        .PS(PS),              // Program Select - determines branch condition polarity
        .Z(Z),                // Zero flag - used for conditional branch decisions
        .out(PC_next)         // Selected next PC value output
    );

endmodule

assignments/hw5-risc-cpu/test/IF_stage_tb.v
`timescale 1ns/1ps

`include "../IF_stage.v"
`include "../instructionMemory.v"
`include "../muxC.v"

module IF_stage_tb();

    // Test inputs
    reg clk;
    reg rst;
    reg [31:0] PC_initial;
    reg [31:0] BrA;         // Branch target address
    reg [31:0] RAA;         // Register jump address
    reg [31:0] JMP;         // Jump target address
    reg [1:0] BS;           // Branch Select
    reg PS;                 // Program Select (single bit)
    reg Z;                  // Zero flag for branch decisions
    
    // Test outputs
    wire [31:0] PC_next;    // Next PC value
    wire [31:0] PC_1;       // PC + 1
    wire [31:0] instruction; // Current instruction
    
    // For direct testing of instruction memory
    reg [31:0] test_addr;
    wire [31:0] test_instruction;
    
    // Timing parameters
    parameter CLK_PERIOD = 10; // Clock period in ns
    
    // Instantiate the IF stage
    IF_stage dut(
        .clk(clk),
        .rst(rst),
        .PC(PC_initial),
        .BrA(BrA),
        .RAA(RAA),
        .JMP(JMP),
        .BS(BS),
        .PS(PS),
        .Z(Z),
        .PC_next(PC_next),
        .PC_1(PC_1),
        .instruction(instruction)
    );
    
    // Instantiate instruction memory for direct testing
    instructionMemory inst_mem_test(
        .addr(test_addr),
        .instruction(test_instruction)
    );
    
    // Clock generation
    initial begin
        clk = 0;
        forever #(CLK_PERIOD/2) clk = ~clk;
    end
    
    // Initialize test values
    task initialize;
        begin
            rst = 1;
            PC_initial = 32'h0;
            BrA = 32'h20;
            RAA = 32'h30;
            JMP = 32'h40;
            BS = 2'b00;
            PS = 1'b0;
            Z = 1'b0;
            test_addr = 32'h0;
        end
    endtask
    
    // Load test instructions into memory
    task load_test_instructions;
        begin
            // Load some test instructions
            dut.inst_mem.memory[0] = 32'h00000000;  // NOP
            dut.inst_mem.memory[1] = 32'h04108000;  // ADD R1, R2, R4
            dut.inst_mem.memory[2] = 32'h0A108000;  // SUB R1, R2, R4
            dut.inst_mem.memory[3] = 32'hE4518000;  // SLT R2, R5, R6
            
            // Also add to the test memory
            inst_mem_test.memory[0] = 32'h00000000;  // NOP
            inst_mem_test.memory[1] = 32'h04108000;  // ADD R1, R2, R4
            inst_mem_test.memory[2] = 32'h0A108000;  // SUB R1, R2, R4
            inst_mem_test.memory[3] = 32'hE4518000;  // SLT R2, R5, R6
        end
    endtask
    
    // Test scenarios
    task test_sequential_fetch;
        begin
            $display("Testing sequential instruction fetch...");
            PC_initial = 32'h0;
            BS = 2'b00;  // Select PC+1
            PS = 1'b0;
            Z = 1'b0;
            #CLK_PERIOD;
            
            if (PC_next !== 32'h1)
                $display("ERROR: PC_next = %h, expected 32'h1", PC_next);
            else
                $display("PASS: PC_next = %h as expected", PC_next);
                
            if (instruction !== 32'h00000000)
                $display("ERROR: Instruction = %h, expected 32'h00000000", instruction);
            else
                $display("PASS: Instruction = %h as expected", instruction);
            
            // Try next address
            PC_initial = 32'h1;
            #CLK_PERIOD;
            
            if (PC_next !== 32'h2)
                $display("ERROR: PC_next = %h, expected 32'h2", PC_next);
            else
                $display("PASS: PC_next = %h as expected", PC_next);
                
            if (instruction !== 32'h04108000)
                $display("ERROR: Instruction = %h, expected 32'h04108000", instruction);
            else
                $display("PASS: Instruction = %h as expected", instruction);
        end
    endtask
    
    task test_branch_taken;
        begin
            $display("Testing branch taken...");
            PC_initial = 32'h2;
            BS = 2'b01;  // Branch
            PS = 1'b0;   // BZ
            Z = 1'b1;    // Zero is true, should branch
            BrA = 32'h20;
            #CLK_PERIOD;
            
            if (PC_next !== 32'h20)
                $display("ERROR: PC_next = %h, expected 32'h20", PC_next);
            else
                $display("PASS: PC_next = %h as expected", PC_next);
        end
    endtask
    
    task test_branch_not_taken;
        begin
            $display("Testing branch not taken...");
            PC_initial = 32'h2;
            BS = 2'b01;  // Branch
            PS = 1'b0;   // BZ
            Z = 1'b0;    // Zero is false, should not branch
            BrA = 32'h20;
            #CLK_PERIOD;
            
            if (PC_next !== 32'h3)
                $display("ERROR: PC_next = %h, expected 32'h3", PC_next);
            else
                $display("PASS: PC_next = %h as expected", PC_next);
        end
    endtask
    
    task test_bnz_taken;
        begin
            $display("Testing BNZ taken...");
            PC_initial = 32'h2;
            BS = 2'b01;  // Branch
            PS = 1'b1;   // BNZ
            Z = 1'b0;    // Zero is false, should branch for BNZ
            BrA = 32'h20;
            #CLK_PERIOD;
            
            if (PC_next !== 32'h20)
                $display("ERROR: PC_next = %h, expected 32'h20", PC_next);
            else
                $display("PASS: PC_next = %h as expected", PC_next);
        end
    endtask
    
    task test_jump_register;
        begin
            $display("Testing jump register...");
            PC_initial = 32'h2;
            BS = 2'b10;  // Jump register
            RAA = 32'h30;
            #CLK_PERIOD;
            
            if (PC_next !== 32'h30)
                $display("ERROR: PC_next = %h, expected 32'h30", PC_next);
            else
                $display("PASS: PC_next = %h as expected", PC_next);
        end
    endtask
    
    task test_jump_immediate;
        begin
            $display("Testing jump immediate...");
            PC_initial = 32'h2;
            BS = 2'b11;  // Jump immediate
            JMP = 32'h40;
            #CLK_PERIOD;
            
            if (PC_next !== 32'h40)
                $display("ERROR: PC_next = %h, expected 32'h40", PC_next);
            else
                $display("PASS: PC_next = %h as expected", PC_next);
        end
    endtask
    
    task test_instruction_memory;
        begin
            $display("Testing instruction memory directly...");
            test_addr = 32'h0;
            #CLK_PERIOD;
            if (test_instruction !== 32'h00000000)
                $display("ERROR: Instruction at addr 0 = %h, expected 32'h00000000", test_instruction);
            else
                $display("PASS: Instruction at addr 0 = %h as expected", test_instruction);
                
            test_addr = 32'h1;
            #CLK_PERIOD;
            if (test_instruction !== 32'h04108000)
                $display("ERROR: Instruction at addr 1 = %h, expected 32'h04108000", test_instruction);
            else
                $display("PASS: Instruction at addr 1 = %h as expected", test_instruction);
                
            test_addr = 32'h2;
            #CLK_PERIOD;
            if (test_instruction !== 32'h0A108000)
                $display("ERROR: Instruction at addr 2 = %h, expected 32'h0A108000", test_instruction);
            else
                $display("PASS: Instruction at addr 2 = %h as expected", test_instruction);
        end
    endtask
    
    // Main test sequence
    initial begin

        // Initialize waveform dumping
        $dumpfile("IF_stage_tb.vcd");
        $dumpvars(0, IF_stage_tb);
        
        $display("Starting IF stage tests...");
        
        // Initialize
        initialize();
        load_test_instructions();
        
        // Reset sequence
        #(CLK_PERIOD * 2);
        rst = 0;
        #(CLK_PERIOD);
        
        // Run tests
        test_sequential_fetch();
        test_branch_taken();
        test_branch_not_taken();
        test_bnz_taken();
        test_jump_register();
        test_jump_immediate();
        test_instruction_memory();
        
        // End simulation
        $display("All IF stage tests completed!");
        #(CLK_PERIOD * 2);
        $finish;
    end

endmodule

assignments/hw5-risc-cpu/test/IF_stage_tb.vcd
$date
	Thu Mar 27 13:39:41 2025
$end
$version
	Icarus Verilog
$end
$timescale
	1ps
$end
$scope module IF_stage_tb $end
$var wire 32 ! test_instruction [31:0] $end
$var wire 32 " instruction [31:0] $end
$var wire 32 # PC_next [31:0] $end
$var wire 32 $ PC_1 [31:0] $end
$var parameter 32 % CLK_PERIOD $end
$var reg 2 & BS [1:0] $end
$var reg 32 ' BrA [31:0] $end
$var reg 32 ( JMP [31:0] $end
$var reg 32 ) PC_initial [31:0] $end
$var reg 1 * PS $end
$var reg 32 + RAA [31:0] $end
$var reg 1 , Z $end
$var reg 1 - clk $end
$var reg 1 . rst $end
$var reg 32 / test_addr [31:0] $end
$scope module dut $end
$var wire 2 0 BS [1:0] $end
$var wire 32 1 BrA [31:0] $end
$var wire 32 2 JMP [31:0] $end
$var wire 32 3 PC [31:0] $end
$var wire 1 * PS $end
$var wire 32 4 RAA [31:0] $end
$var wire 1 , Z $end
$var wire 1 - clk $end
$var wire 1 . rst $end
$var wire 32 5 instruction [31:0] $end
$var wire 32 6 PC_next [31:0] $end
$var wire 32 7 PC_1 [31:0] $end
$scope module inst_mem $end
$var wire 32 8 addr [31:0] $end
$var wire 32 9 instruction [31:0] $end
$var integer 32 : i [31:0] $end
$upscope $end
$scope module mux_c $end
$var wire 2 ; BS [1:0] $end
$var wire 32 < BrA [31:0] $end
$var wire 32 = JMP [31:0] $end
$var wire 32 > PC_1 [31:0] $end
$var wire 1 * PS $end
$var wire 32 ? RAA [31:0] $end
$var wire 1 , Z $end
$var wire 32 @ top_path [31:0] $end
$var wire 32 A out [31:0] $end
$var wire 1 B branch_condition $end
$var wire 32 C bottom_path [31:0] $end
$var wire 1 D BS1 $end
$var wire 1 E BS0 $end
$upscope $end
$upscope $end
$scope module inst_mem_test $end
$var wire 32 F addr [31:0] $end
$var wire 32 G instruction [31:0] $end
$var integer 32 H i [31:0] $end
$upscope $end
$scope task initialize $end
$upscope $end
$scope task load_test_instructions $end
$upscope $end
$scope task test_bnz_taken $end
$upscope $end
$scope task test_branch_not_taken $end
$upscope $end
$scope task test_branch_taken $end
$upscope $end
$scope task test_instruction_memory $end
$upscope $end
$scope task test_jump_immediate $end
$upscope $end
$scope task test_jump_register $end
$upscope $end
$scope task test_sequential_fetch $end
$upscope $end
$upscope $end
$enddefinitions $end
$comment Show the parameter values. $end
$dumpall
b1010 %
$end
#0
$dumpvars
b10000000000 H
b0 G
b0 F
0E
0D
b110000 C
0B
b1 A
b1 @
b110000 ?
b1 >
b1000000 =
b100000 <
b0 ;
b10000000000 :
b0 9
b0 8
b1 7
b1 6
b0 5
b110000 4
b0 3
b1000000 2
b100000 1
b0 0
b0 /
1.
0-
0,
b110000 +
0*
b0 )
b1000000 (
b100000 '
b0 &
b1 $
b1 #
b0 "
b0 !
$end
#5000
1-
#10000
0-
#15000
1-
#20000
0-
0.
#25000
1-
#30000
0-
#35000
1-
#40000
b10 #
b10 6
b10 A
b10 @
b100000100001000000000000000 "
b100000100001000000000000000 5
b100000100001000000000000000 9
0-
b10 $
b10 7
b10 >
b1 )
b1 3
b1 8
#45000
1-
#50000
b1000000 C
b100000 #
b100000 6
b100000 A
1B
1E
b100000 @
b1010000100001000000000000000 "
b1010000100001000000000000000 5
b1010000100001000000000000000 9
0-
1,
b1 &
b1 0
b1 ;
b11 $
b11 7
b11 >
b10 )
b10 3
b10 8
#55000
1-
#60000
b11 #
b11 6
b11 A
b11 @
0B
0-
0,
#65000
1-
#70000
b100000 #
b100000 6
b100000 A
b100000 @
1B
0-
1*
#75000
1-
#80000
b11 @
b110000 #
b110000 6
b110000 A
b110000 C
1D
0E
0-
b10 &
b10 0
b10 ;
#85000
1-
#90000
b1000000 #
b1000000 6
b1000000 A
b100000 @
b1000000 C
1E
0-
b11 &
b11 0
b11 ;
#95000
1-
#100000
0-
#105000
1-
#110000
b100000100001000000000000000 !
b100000100001000000000000000 G
0-
b1 /
b1 F
#115000
1-
#120000
b1010000100001000000000000000 !
b1010000100001000000000000000 G
0-
b10 /
b10 F
