assignments/hw5-risc-cpu/muxD.v
module muxD(
    input wire [31:0] ALU_result,  // ALU output
    input wire [31:0] mem_data,    // Memory data
    input wire N_xor_V,            // N⊕V for SLT instruction
    input wire [1:0] MD,           // Memory Data select (2 bits)
    output reg [31:0] out          // Selected output
);
    /*
     * Multiplexer D - Pipeline Stage: Write Back (WB)
     * 
     * This multiplexer selects the data to be written back to registers.
     * It has three inputs selected by 2-bit MD control:
     * - MD = 00: ALU_result - Result from arithmetic/logical operations
     * - MD = 01: mem_data - Data loaded from memory
     * - MD = 10: {31'b0, N⊕V} - Sign bit for SLT instruction
     * 
     * In the diagram, this is shown at the bottom with inputs 0, 1, and 2.
     */

    // Select between ALU result, memory data, and N⊕V
    always @(*) begin
        case (MD)
            2'b00: out = ALU_result;            // ALU result
            2'b01: out = mem_data;              // Memory data
            2'b10: out = {31'b0, N_xor_V};      // N⊕V sign extended for SLT
            default: out = ALU_result;          // Default
        endcase
    end

endmodule

assignments/hw5-risc-cpu/WB_stage.v
module WB_stage(
    // Data inputs
    input wire [31:0] ALU_result,   // ALU computation result from EX stage - used for most arithmetic/logical operations
    input wire [31:0] mem_data,     // Data read from memory in EX stage - used for load operations
    input wire N_xor_V,             // N XOR V condition flag from EX stage - used for SLT (Set Less Than) instruction
    // Control inputs
    input wire [1:0] MD,            // Memory Data select control - determines data source for register write: 00=ALU, 01=memory, 10=N⊕V
    input wire RW,                  // Register Write enable - controls whether register file is written to
    input wire [4:0] DR,            // Destination Register number - specifies which register to write to (R0-R31)
    // Outputs
    output wire [31:0] WB_data,     // Final data value to write to register file - selected from the three input sources
    output wire [4:0] WB_addr,      // Register address to write to (simply passes through DR)
    output wire WB_en               // Final write enable signal for register file (simply passes through RW)
);
    /*
     * Write Back (WB) Stage - Fourth and final stage of the 4-stage RISC CPU pipeline
     *
     * Purpose and Operation:
     * ---------------------
     * The WB stage is responsible for selecting the appropriate data to write back
     * to the register file and generating the control signals for the write operation.
     * 
     * This stage represents the completion of instruction execution and is where
     * the CPU finally updates the architectural state visible to the programmer.
     * 
     * Key Functions:
     * -------------
     * 1. Data Selection - Choose the appropriate value to write to registers:
     *    - ALU result for arithmetic, logical, and shift operations
     *    - Memory data for load operations
     *    - N⊕V flag for SLT (Set Less Than) instruction
     * 
     * 2. Register Write Control - Generate the signals needed to:
     *    - Specify which register to write to (WB_addr from DR)
     *    - Enable or disable the write operation (WB_en from RW)
     * 
     * The MuxD component has three inputs selected by the 2-bit MD control signal:
     * - MD=00: ALU_result (from arithmetic/logical operations)
     * - MD=01: mem_data (from load operations)
     * - MD=10: N⊕V flag (extended to 32 bits for SLT instruction)
     *
     * Note: When RW=0, no register write occurs regardless of other signals.
     */

    // MuxD - Write Back Data Selection Multiplexer
    // Selects the appropriate data source for register write operations
    // based on the type of instruction being executed
    muxD mux_d(
        .ALU_result(ALU_result),   // ALU computation result (for arithmetic/logical operations)
        .mem_data(mem_data),       // Memory data (for load operations)
        .N_xor_V(N_xor_V),         // N XOR V condition flag (for SLT instruction)
        .MD(MD),                   // Memory Data select control signal (2 bits)
        .out(WB_data)              // Selected data output to register file
    );

    // Write back control signals - Pass through from pipeline registers
    // These signals connect directly to the register file to control the write operation
    assign WB_addr = DR;           // Destination Register number becomes the write address
    assign WB_en = RW;             // Register Write enable becomes the write enable signal
    
    // Debug output - Displays register write information when enabled
    // This helps track the flow of data from the pipeline to the register file
    always @(*) begin
        if (RW)
            $display("WB DEBUG: Write enabled DR=%d WB_data=%h", DR, WB_data);
    end

endmodule

assignments/hw5-risc-cpu/test/WB_stage_tb.v
`timescale 1ns/1ps

`include "../WB_stage.v"
`include "../muxD.v"

module WB_stage_tb();

    // Test signals
    reg [31:0] ALU_result;
    reg [31:0] mem_data;
    reg N_xor_V;
    reg [1:0] MD;
    reg RW;
    reg [4:0] DR;
    
    // Outputs
    wire [31:0] WB_data;
    wire [4:0] WB_addr;
    wire WB_en;
    
    // Instantiate the WB stage
    WB_stage dut(
        .ALU_result(ALU_result),
        .mem_data(mem_data),
        .N_xor_V(N_xor_V),
        .MD(MD),
        .RW(RW),
        .DR(DR),
        .WB_data(WB_data),
        .WB_addr(WB_addr),
        .WB_en(WB_en)
    );
    
    // Test MD selection task
    task test_md_selection;
        input [1:0] md_val;
        input [31:0] alu_val;
        input [31:0] mem_val;
        input n_xor_v_val;
        input [31:0] expected_data;
        begin
            // Set up inputs
            ALU_result = alu_val;
            mem_data = mem_val;
            N_xor_V = n_xor_v_val;
            MD = md_val;
            
            #2; // Allow signals to propagate
            
            // Display info for debugging
            $display("Testing MD selection: MD=%b, ALU=%h, MEM=%h, N_xor_V=%b", 
                     md_val, alu_val, mem_val, n_xor_v_val);
            
            // Verify results
            if (WB_data !== expected_data)
                $display("FAIL: WB_data = %h, expected %h for MD=%b", 
                         WB_data, expected_data, md_val);
            else
                $display("PASS: WB_data = %h as expected for MD=%b", 
                         WB_data, md_val);
        end
    endtask
    
    // Test control signal propagation
    task test_control_signals;
        input rw_val;
        input [4:0] dr_val;
        begin
            // Set up inputs
            RW = rw_val;
            DR = dr_val;
            
            #2; // Allow signals to propagate
            
            // Display info for debugging
            $display("Testing control signals: RW=%b, DR=%h", rw_val, dr_val);
            
            // Verify results
            if (WB_addr !== dr_val)
                $display("FAIL: WB_addr = %h, expected %h", WB_addr, dr_val);
            else
                $display("PASS: WB_addr = %h as expected", WB_addr);
            
            if (WB_en !== rw_val)
                $display("FAIL: WB_en = %b, expected %b", WB_en, rw_val);
            else
                $display("PASS: WB_en = %b as expected", WB_en);
        end
    endtask
    
    // Main test sequence
    initial begin
        // Initialize waveform dumping
        $dumpfile("WB_stage_tb.vcd");
        $dumpvars(0, WB_stage_tb);
        
        // Initialize
        ALU_result = 32'h0;
        mem_data = 32'h0;
        N_xor_V = 1'b0;
        MD = 2'b00;
        RW = 1'b0;
        DR = 5'h0;
        
        #10; // Wait a bit
        
        $display("=== WB Stage Unit Test ===");
        
        $display("\n=== Testing MD Selection ===");
        // Test MD = 00 (select ALU_result)
        test_md_selection(2'b00, 32'hAAAAAAAA, 32'hBBBBBBBB, 1'b0, 32'hAAAAAAAA);
        
        // Test MD = 01 (select mem_data)
        test_md_selection(2'b01, 32'hAAAAAAAA, 32'hBBBBBBBB, 1'b0, 32'hBBBBBBBB);
        
        // Test MD = 10 (select N_xor_V, extended to 32 bits)
        test_md_selection(2'b10, 32'hAAAAAAAA, 32'hBBBBBBBB, 1'b0, 32'h00000000);
        test_md_selection(2'b10, 32'hAAAAAAAA, 32'hBBBBBBBB, 1'b1, 32'h00000001);
        
        $display("\n=== Testing Control Signal Propagation ===");
        // Test RW = 0, DR = 0
        test_control_signals(1'b0, 5'h00);
        
        // Test RW = 1, DR = 10
        test_control_signals(1'b1, 5'h0A);
        
        // Test RW = 1, DR = 31
        test_control_signals(1'b1, 5'h1F);
        
        // Test RW = 0, DR = 15
        test_control_signals(1'b0, 5'h0F);
        
        // End test
        $display("\n=== WB Stage Unit Test Complete ===");
        #10;
        $finish;
    end

endmodule

assignments/hw5-risc-cpu/test/WB_stage_tb.vcd
$date
	Thu Mar 27 14:21:40 2025
$end
$version
	Icarus Verilog
$end
$timescale
	1ps
$end
$scope module WB_stage_tb $end
$var wire 1 ! WB_en $end
$var wire 32 " WB_data [31:0] $end
$var wire 5 # WB_addr [4:0] $end
$var reg 32 $ ALU_result [31:0] $end
$var reg 5 % DR [4:0] $end
$var reg 2 & MD [1:0] $end
$var reg 1 ' N_xor_V $end
$var reg 1 ( RW $end
$var reg 32 ) mem_data [31:0] $end
$scope module dut $end
$var wire 32 * ALU_result [31:0] $end
$var wire 5 + DR [4:0] $end
$var wire 2 , MD [1:0] $end
$var wire 1 ' N_xor_V $end
$var wire 1 ( RW $end
$var wire 5 - WB_addr [4:0] $end
$var wire 1 ! WB_en $end
$var wire 32 . mem_data [31:0] $end
$var wire 32 / WB_data [31:0] $end
$scope module mux_d $end
$var wire 32 0 ALU_result [31:0] $end
$var wire 2 1 MD [1:0] $end
$var wire 1 ' N_xor_V $end
$var wire 32 2 mem_data [31:0] $end
$var reg 32 3 out [31:0] $end
$upscope $end
$upscope $end
$scope task test_control_signals $end
$var reg 5 4 dr_val [4:0] $end
$var reg 1 5 rw_val $end
$upscope $end
$scope task test_md_selection $end
$var reg 32 6 alu_val [31:0] $end
$var reg 32 7 expected_data [31:0] $end
$var reg 2 8 md_val [1:0] $end
$var reg 32 9 mem_val [31:0] $end
$var reg 1 : n_xor_v_val $end
$upscope $end
$upscope $end
$enddefinitions $end
$comment Show the parameter values. $end
$dumpall
$end
#0
$dumpvars
x:
bx 9
bx 8
bx 7
bx 6
x5
bx 4
b0 3
b0 2
b0 1
b0 0
b0 /
b0 .
b0 -
b0 ,
b0 +
b0 *
b0 )
0(
0'
b0 &
b0 %
b0 $
b0 #
b0 "
0!
$end
#10000
b10101010101010101010101010101010 "
b10101010101010101010101010101010 /
b10101010101010101010101010101010 3
b10111011101110111011101110111011 )
b10111011101110111011101110111011 .
b10111011101110111011101110111011 2
b10101010101010101010101010101010 $
b10101010101010101010101010101010 *
b10101010101010101010101010101010 0
b10101010101010101010101010101010 7
0:
b10111011101110111011101110111011 9
b10101010101010101010101010101010 6
b0 8
#12000
b10111011101110111011101110111011 "
b10111011101110111011101110111011 /
b10111011101110111011101110111011 3
b1 &
b1 ,
b1 1
b10111011101110111011101110111011 7
b1 8
#14000
b0 "
b0 /
b0 3
b10 &
b10 ,
b10 1
b0 7
b10 8
#16000
b1 "
b1 /
b1 3
1'
b1 7
1:
#18000
b0 4
05
#20000
b1010 #
b1010 -
b1010 %
b1010 +
1!
1(
b1010 4
15
#22000
b11111 #
b11111 -
b11111 %
b11111 +
b11111 4
#24000
b1111 #
b1111 -
b1111 %
b1111 +
0!
0(
b1111 4
05
