assignments/hw1-basic/hw1-basic.v
`timescale 1ns / 1ps

//=============================================================================
// HW1 Basic Verilog
// Mark Dannemiller
//=============================================================================

module hw1(
    input A,
    input B,
    input C,
    input D,
    output out
);

    assign out = (A | D) & (~B | C);
    
endmodule

assignments/hw1-basic/hw1-basic_tb.v
`timescale 1ns / 1ps
`include "./hw1-basic.v"

//=============================================================================
// HW1 Basic Verilog
// Mark Dannemiller
//=============================================================================

module hw1_tb;

    // Inputs
    reg A;
    reg B;
    reg C;
    reg D;

    // Outputs
    wire out;

    // Instantiate the Unit Under Test (UUT)
    hw1 uut (
        .A(A), 
        .B(B), 
        .C(C),
        .D(D), 
        .out(out)
    );

    integer i;

    initial begin
        // Initialize Inputs
        $dumpfile("hw1-basic_tb.vcd");
        $dumpvars(0, hw1_tb);
        $display("Homework 1 Basic Testbench");
        
        // Wait 100 ns for global reset to finish
        #100;
        
        for(i=0; i<16; i = i + 1)
          begin
            {A,B,C,D} = i;
            #10;
          end

    end
endmodule

assignments/hw1-basic/hw1-basic_tb.vcd
$date
	Tue Jan 21 13:26:25 2025
$end
$version
	Icarus Verilog
$end
$timescale
	1ps
$end
$scope module hw1_tb $end
$var wire 1 ! out $end
$var reg 1 " A $end
$var reg 1 # B $end
$var reg 1 $ C $end
$var reg 1 % D $end
$var integer 32 & i [31:0] $end
$scope module uut $end
$var wire 1 " A $end
$var wire 1 # B $end
$var wire 1 $ C $end
$var wire 1 % D $end
$var wire 1 ! out $end
$upscope $end
$upscope $end
$enddefinitions $end
$comment Show the parameter values. $end
$dumpall
$end
#0
$dumpvars
bx &
x%
x$
x#
x"
x!
$end
#100000
0!
0"
0#
0$
0%
b0 &
#110000
1!
1%
b1 &
#120000
0!
1$
0%
b10 &
#130000
1!
1%
b11 &
#140000
0!
1#
0$
0%
b100 &
#150000
1%
b101 &
#160000
1$
0%
b110 &
#170000
1!
1%
b111 &
#180000
1!
1"
0#
0$
0%
b1000 &
#190000
1%
b1001 &
#200000
1$
0%
b1010 &
#210000
1%
b1011 &
#220000
0!
1#
0$
0%
b1100 &
#230000
1%
b1101 &
#240000
1!
1$
0%
b1110 &
#250000
1%
b1111 &
#260000
b10000 &
